Basic-Seq-Logic-1/seq_logic.sv
module seq_logic(input logic A, select, CLK,
                 output logic F);

    logic mux_out; // define internal var - output of multiplexer

    assign mux_out = select ? A : ~F; // continuous assignment
    // mux_out = A if select asserted
    // mux_out = not(F) if select de-asserted

    always_ff @ (posedge CLK) // flip-flop cyclic loop
    // this block executes on every rising CLK edge 0->1
    begin
        F <= mux_out; 
        // non-blocking operator <= used in cyclic assignment
    end

endmodule

Basic-Seq-Logic-1/seq_logic_tb.sv
`timescale 1ns/1ps 
// define simulation time unit = 1 ns and time resolution 1 ps

`include "seq_logic.sv" // include device under test (DUT)

module seq_logic_tb; // testbench has no I/O

    logic A, select, CLK, F; // define internal vars of testbench
    seq_logic dut(A, select, CLK, F); // initialise DUT

    
    // define CLK signal with period 20 ns:
    always // runs simultaneously w other code and updates CLK every 10 ns
    begin
        CLK = 1; #10; CLK = 0; #10; // change CLK high-low every 10 ns
    end

    initial // single-pass code block initialisation
    begin
        $dumpfile("seq_logic_tb.vcd");
        // defines the VCD file where var changes of the testbench are dumped
        $dumpvars(0, seq_logic_tb);
        // specify to dump this testbench file on the VCD file defined above

        // testing I/O of DUT:
        A = 0; select = 1;
        #15; // to unsync var changes from CLK changes
        A = 1;
        #10;
        A = 0;
        #10;
        select = 0;
        #10;
        A = 1;
        #10;
        A = 0;
        #10;
        select = 1;
        #10;
        $finish;
    end // end stimuli

    initial
    begin
        $monitor("t = %3d, A = %d select = %d F = %d", $time, A, select, F);
        // display timing and vars A, select, F to the monitor
    end

endmodule

Basic-Seq-Logic-1/seq_logic_tb.vcd
$date
	Sun Feb 06 01:36:26 2022
$end
$version
	Icarus Verilog
$end
$timescale
	1ps
$end
$scope module seq_logic_tb $end
$var wire 1 ! F $end
$var reg 1 " A $end
$var reg 1 # CLK $end
$var reg 1 $ select $end
$scope module dut $end
$var wire 1 " A $end
$var wire 1 # CLK $end
$var wire 1 $ select $end
$var wire 1 % mux_out $end
$var reg 1 ! F $end
$upscope $end
$upscope $end
$enddefinitions $end
#0
$dumpvars
0%
1$
1#
0"
x!
$end
#10000
0#
#15000
1%
1"
#20000
1!
1#
#25000
0%
0"
#30000
0#
#35000
0$
#40000
1%
0!
1#
#45000
1"
#50000
0#
#55000
0"
#60000
0%
1!
1#
#65000
1$
